text2system/__init__.py
text2system/aiengine.py
text2system/analyticsengine.py
text2system/autonomouscontroller.py
text2system/businessprocessengine.py
text2system/domainengine.py
text2system/externalservice.py
text2system/integrationengine.py
text2system/interfacecontroller.py
text2system/multchannelapp.py
text2system/securityengine.py
text2system/user.py
text2system-0.0.8.dist-info/LICENSE
text2system-0.0.8.dist-info/METADATA
text2system-0.0.8.dist-info/WHEEL
text2system-0.0.8.dist-info/top_level.txt
text2system-0.0.8.dist-info/RECORD
