Metadata-Version: 2.1
Name: text2system
Version: 0.0.8
Summary: A self-adaptative architecture implementation.
Home-page: https://github.com/andersonmgomes/text2system
Author: Anderson Martins Gomes
Author-email: andersonmg@gmail.com
License: UNKNOWN
Platform: UNKNOWN
Classifier: Programming Language :: Python :: 3
Classifier: License :: OSI Approved :: MIT License
Classifier: Operating System :: OS Independent
Requires-Python: >=3.6
License-File: LICENSE
